IbmDeveloperworksQuanbuWenzhangDiyiBufenFix1/README.md
IbmDeveloperworksQuanbuWenzhangDiyiBufenFix1/__init__.py
IbmDeveloperworksQuanbuWenzhangDiyiBufenFix1/__main__.py
IbmDeveloperworksQuanbuWenzhangDiyiBufenFix1/file.epub
IbmDeveloperworksQuanbuWenzhangDiyiBufenFix1/index.html
IbmDeveloperworksQuanbuWenzhangDiyiBufenFix1/css/__init__.py
IbmDeveloperworksQuanbuWenzhangDiyiBufenFix1/css/annotations.css
IbmDeveloperworksQuanbuWenzhangDiyiBufenFix1/css/main.css
IbmDeveloperworksQuanbuWenzhangDiyiBufenFix1/css/normalize.css
IbmDeveloperworksQuanbuWenzhangDiyiBufenFix1/css/popup.css
IbmDeveloperworksQuanbuWenzhangDiyiBufenFix1/font/__init__.py
IbmDeveloperworksQuanbuWenzhangDiyiBufenFix1/font/fontello.eot
IbmDeveloperworksQuanbuWenzhangDiyiBufenFix1/font/fontello.svg
IbmDeveloperworksQuanbuWenzhangDiyiBufenFix1/font/fontello.ttf
IbmDeveloperworksQuanbuWenzhangDiyiBufenFix1/font/fontello.woff
IbmDeveloperworksQuanbuWenzhangDiyiBufenFix1/img/__init__.py
IbmDeveloperworksQuanbuWenzhangDiyiBufenFix1/img/annotator-glyph-sprite.png
IbmDeveloperworksQuanbuWenzhangDiyiBufenFix1/img/annotator-icon-sprite.png
IbmDeveloperworksQuanbuWenzhangDiyiBufenFix1/img/apple-touch-icon.png
IbmDeveloperworksQuanbuWenzhangDiyiBufenFix1/img/cancelfullscreen.png
IbmDeveloperworksQuanbuWenzhangDiyiBufenFix1/img/close.png
IbmDeveloperworksQuanbuWenzhangDiyiBufenFix1/img/fullscreen.png
IbmDeveloperworksQuanbuWenzhangDiyiBufenFix1/img/loader.gif
IbmDeveloperworksQuanbuWenzhangDiyiBufenFix1/img/menu-icon.png
IbmDeveloperworksQuanbuWenzhangDiyiBufenFix1/img/save.png
IbmDeveloperworksQuanbuWenzhangDiyiBufenFix1/img/saved.png
IbmDeveloperworksQuanbuWenzhangDiyiBufenFix1/img/settings-s.png
IbmDeveloperworksQuanbuWenzhangDiyiBufenFix1/img/settings.png
IbmDeveloperworksQuanbuWenzhangDiyiBufenFix1/img/star.png
IbmDeveloperworksQuanbuWenzhangDiyiBufenFix1/js/__init__.py
IbmDeveloperworksQuanbuWenzhangDiyiBufenFix1/js/epub.js
IbmDeveloperworksQuanbuWenzhangDiyiBufenFix1/js/epub.min.js
ibm_developerworks_quanbu_wenzhang_diyi_bufen_fix1-2025.3.25.1.dist-info/METADATA
ibm_developerworks_quanbu_wenzhang_diyi_bufen_fix1-2025.3.25.1.dist-info/WHEEL
ibm_developerworks_quanbu_wenzhang_diyi_bufen_fix1-2025.3.25.1.dist-info/entry_points.txt
ibm_developerworks_quanbu_wenzhang_diyi_bufen_fix1-2025.3.25.1.dist-info/top_level.txt
ibm_developerworks_quanbu_wenzhang_diyi_bufen_fix1-2025.3.25.1.dist-info/RECORD
